horizon_py/__init__.py
horizon_py/api.py
horizon_py/deep_horizon.py
horizon_py/helpers.py
horizon_py-0.1.1.dist-info/DESCRIPTION.rst
horizon_py-0.1.1.dist-info/METADATA
horizon_py-0.1.1.dist-info/RECORD
horizon_py-0.1.1.dist-info/WHEEL
horizon_py-0.1.1.dist-info/metadata.json
horizon_py-0.1.1.dist-info/top_level.txt
