Metadata-Version: 2.0
Name: horizon-py
Version: 0.1.1
Summary: DeepHorizon API Client
Home-page: https://github.com/deep-horizon/horizon_py
Author: Ben Whittle
Author-email: benwhittle31@gmail.com
License: MIT
Platform: UNKNOWN
Requires-Dist: requests
